Metadata-Version: 2.1
Name: dias-uteis-rpa
Version: 1.0.6
Summary: Classe com métodos referente dias uteis do Brazil
Home-page: https://github.com/edenilsonsantos/dias-uteis-brasil
Author: Edenilson Fernandes dos Santos
Author-email: santoeen@gmail.com
License: MIT License
Project-URL: repository, https://github.com/edenilsonsantos/dias-uteis-brasil
Keywords: dias uteis brazil brasil feriados nacionais
Classifier: Programming Language :: Python :: 3
Classifier: License :: OSI Approved :: MIT License
Classifier: Operating System :: OS Independent
Requires-Python: >=3.8
License-File: LICENSE
